.gitignore
.nojekyll
.travis.yml
LICENSE
Makefile
README.rst
pyproject.toml
requirements.txt
setup.py
tox.ini
docker/Dockerfile
docker/Makefile
docs/.nojekyll
docs/Makefile
docs/conf.py
docs/index.rst
docs/make.bat
docs/appurls/archive_urls.rst
docs/appurls/file_urls.rst
docs/appurls/index.rst
docs/appurls/resolution.rst
docs/appurls/usage.rst
docs/appurls/web_urls.rst
docs/rowgenerators/index.rst
docs/rowpipe/index.rst
docs/transforms/index.rst
docs/valuetypes/index.rst
rowgenerators/__init__.py
rowgenerators/cli.py
rowgenerators/core.py
rowgenerators/exceptions.py
rowgenerators/rowproxy.py
rowgenerators/source.py
rowgenerators/table.py
rowgenerators/util.py
rowgenerators.egg-info/PKG-INFO
rowgenerators.egg-info/SOURCES.txt
rowgenerators.egg-info/dependency_links.txt
rowgenerators.egg-info/entry_points.txt
rowgenerators.egg-info/requires.txt
rowgenerators.egg-info/top_level.txt
rowgenerators/appurl/__init__.py
rowgenerators/appurl/cli.py
rowgenerators/appurl/enumerate.py
rowgenerators/appurl/sql.py
rowgenerators/appurl/url.py
rowgenerators/appurl/util.py
rowgenerators/appurl/archive/__init__.py
rowgenerators/appurl/archive/zip.py
rowgenerators/appurl/file/__init__.py
rowgenerators/appurl/file/app.py
rowgenerators/appurl/file/csv.py
rowgenerators/appurl/file/excel.py
rowgenerators/appurl/file/file.py
rowgenerators/appurl/file/hdf5.py
rowgenerators/appurl/file/program.py
rowgenerators/appurl/file/python.py
rowgenerators/appurl/file/shapefile.py
rowgenerators/appurl/file/stata.py
rowgenerators/appurl/test/__init__.py
rowgenerators/appurl/test/support.py
rowgenerators/appurl/test/test_basic.py
rowgenerators/appurl/test/test_issues.py
rowgenerators/appurl/test/test_parse_url.py
rowgenerators/appurl/test/test_data/__init__.py
rowgenerators/appurl/test/test_data/components.csv
rowgenerators/appurl/test/test_data/joins.csv
rowgenerators/appurl/test/test_data/sources.csv
rowgenerators/appurl/test/test_data/stata.dta
rowgenerators/appurl/test/test_data/stata_package.zip
rowgenerators/appurl/test/test_data/url_classes.csv
rowgenerators/appurl/test/test_data/urls.csv
rowgenerators/appurl/test/test_data/crazy_headers/crazy_body.xls
