Metadata-Version: 2.1
Name: rowgenerators
Version: 0.9.21
Summary: Generate row data from a variety of file formats
Home-page: https://github.com/Metatab/rowgenerator.git
Author: Eric Busboom
Author-email: eric@civicknowledge.com
License: MIT
Platform: UNKNOWN
Classifier: Development Status :: 4 - Beta
Classifier: Environment :: Web Environment
Classifier: Intended Audience :: Developers
Classifier: License :: OSI Approved :: MIT License
Classifier: Operating System :: OS Independent
Classifier: Programming Language :: Python
Classifier: Programming Language :: Python :: 3.5
Classifier: Topic :: Software Development :: Debuggers
Classifier: Topic :: Software Development :: Libraries :: Python Modules
Provides-Extra: geo
